py17track/__init__.py
py17track/client.py
py17track/errors.py
py17track/package.py
py17track/profile.py
py17track/track.py
py17track-2021.12.2.dist-info/LICENSE
py17track-2021.12.2.dist-info/WHEEL
py17track-2021.12.2.dist-info/METADATA
py17track-2021.12.2.dist-info/RECORD
