Metadata-Version: 2.1
Name: py17track
Version: 2021.12.2
Summary: A Simple Python API for 17track.net
Home-page: https://github.com/bachya/py17track
License: MIT
Author: Aaron Bach
Author-email: bachya1208@gmail.com
Requires-Python: >=3.6.1,<4.0.0
Classifier: License :: OSI Approved :: MIT License
Classifier: Programming Language :: Python
Classifier: Programming Language :: Python :: 3
Classifier: Programming Language :: Python :: 3.10
Classifier: Programming Language :: Python :: 3.6
Classifier: Programming Language :: Python :: 3.7
Classifier: Programming Language :: Python :: 3.8
Classifier: Programming Language :: Python :: 3.9
Classifier: Programming Language :: Python :: Implementation :: CPython
Classifier: Programming Language :: Python :: Implementation :: PyPy
Requires-Dist: aiohttp (>=3.8.0)
Requires-Dist: attrs (>=19.3)
Requires-Dist: pytz (>=2021.1)
Project-URL: Repository, https://github.com/bachya/py17track
